[
  {
    "id": 0,
    "name": "Champiñones Locos",
    "description": "Salteados y preparados con jamon, queso y especias de finas hierbas.",
    "price": 139.50,
    "imageUrl": "https://locosxlaparrilla.com/wp-content/uploads/2015/02/Receta-recetas-locos-x-la-parrilla-locosxlaparrilla-receta-champiñones-ajillo-champiñones-ajillo-receta-champiñones-champiñones-2.jpg",
    "idCategory": 1,
    "idIngredientes": "1|2|3"
  },
  {
    "id": 1,
    "name": "Nuggets de Pollo",
    "description": "Acompañados con papa francesa y canasta de frutas y helado",
    "price": 79.50,
    "imageUrl": "https://locosxlaparrilla.com/wp-content/uploads/2015/02/Receta-recetas-locos-x-la-parrilla-locosxlaparrilla-receta-champiñones-ajillo-champiñones-ajillo-receta-champiñones-champiñones-2.jpg",
    "idCategory": 2,
    "idIngredientes": "5|7|8"
  }
]